{
  "name": "Alejandro McCoy",
  "age": 50,
  "address": {
    "street": "Fiib Heights",
    "city": "Ciledpa",
    "state": "MI",
    "zip": "53941"
  },
  "contact": {
    "phone": "(834) 839-5112",
    "servicePhone": "800884412"
  },
  "birthday": "1970-07-20T21:41:20.171Z",
  "ip": "106.197.188.213",
  "foo": "bar",
  "profile": {
    "about": "Hal itnuvow wo ezacofe jepse bus kimol cuwatafi teh ru cag enu ajogeto. Rizar hac gakci huhec goitne eve jefajriw poton suzbet teeppem sob ara ju wamwo. Wawko wi ecubva zipruvma revisdid lol cas vivniczu ropkikbu dopobuc welijcag dah dolhikes nir mihuw obfe evgugrum. Fage nimomizew wersun wemav te liruwpo bowimun kovi he cen uzezaj nozwapapa habkordu asvediva ken befwilob isiho. Beesa taiwu uvefu zubtait okedeg wot ga da gutaep ichigwa wifermu maniuki ewabo ewja.",
    "bio": "So bid najkifef mo kis oharulzos foziwu zibceg muwagufib kuubid josjoz suwtuh on readocil jubaga. Gof hik uzbak loserza fa ipwarcuh jigbucozo noh melwur lulbodku inifulko lu ihekusoca numlun wacfezzob bi. Zecejav zolso wi ejugef roh fushefwu deecba zud oka wuap obafi piwhip dav. Isco ne kuub riczacse ati omagivfe ku waev mom maak vana re ri. Zozirti sebbaposa ugfepam ozurur igianmev kawpogjez baavfu wem va pafdob wibwohus ohigot tij. Je koret rikla nowra itazuwe hu zauf fanirooze zorgepub ni favcomit su viutudu cegefoj pomo. Gen jik riorawi epva ki mernisic fulur davaz um luz muzoj zuv ogmig maadgab direna piwus fop."
  },
  "apiKey": "530f1dadcdfc70367f8e265fe0722e4ee8687341fa30798161ac8cc85aca522d",
  "currency": {
    "code": "MYR",
    "name": "Malaysia Ringgit"
  }
}