{
  "name": "Brian Henderson",
  "age": 49,
  "address": {
    "street": "Habiri Park",
    "city": "Dorefaha",
    "state": "HI",
    "zip": "24520"
  },
  "contact": {
    "phone": "(509) 438-4677",
    "servicePhone": "800714966"
  },
  "birthday": "1984-12-30T21:11:15.262Z",
  "ip": "17.239.182.103",
  "foo": "bar",
  "profile": {
    "about": "Opijawat vefmid jokef emi denucaw omuduj nijap cug jobecfil sursep goozka la jolohug roiwgut osozacdiz goorgad valonbi kihcefe. Ca haciw huvsis oru cu lol sivjiltur tac eja fis nose laib. Cosoube oz lidowomu ijuagoif ki uhzu sugizaf tezawila ju li fen korgajdo jab nova custub.",
    "bio": "Dewvaru ulije ukkusor ive wij lo wocec ed ifuneom nanhaigu efefiprep zacehuji vuoda ca mifcel sadwo winte. Vuhsu naajijon pamwuzcu sapooj ipuwu no hookeef wasofop kariza jup zi nen mih vupacdog atuwi non. Sif love mapo nu udiubu nawpessos vunzaz ivusodew urlipteb tidze pe izmoj ofuoguis curvelak mab. Ridwatwe uvwam potap mam peza cotmef duzsulpi guw vuwe retpo ozemaatu fuwnuw dus upe up viicbe. Of doruik eglas gar duas poget mipos gautvi su ruc avrifuk juboh fokawo wo."
  },
  "apiKey": "d0c09f9b6699a594e231a4ae6ef939013d1b7c39e7136edf6c3238a4f966810a",
  "currency": {
    "code": "STD",
    "name": "São Tomé and Príncipe Dobra"
  }
}